COPYRIGHT.txt
LICENSE.txt
MANIFEST.in
README.rst
bootstrap.py
setup.py
docs/HISTORY.txt
src/z3c/__init__.py
src/z3c.taskqueue.egg-info/PKG-INFO
src/z3c.taskqueue.egg-info/SOURCES.txt
src/z3c.taskqueue.egg-info/dependency_links.txt
src/z3c.taskqueue.egg-info/entry_points.txt
src/z3c.taskqueue.egg-info/namespace_packages.txt
src/z3c.taskqueue.egg-info/not-zip-safe
src/z3c.taskqueue.egg-info/requires.txt
src/z3c.taskqueue.egg-info/top_level.txt
src/z3c/taskqueue/README.txt
src/z3c/taskqueue/__init__.py
src/z3c/taskqueue/baseservice.py
src/z3c/taskqueue/configure.zcml
src/z3c/taskqueue/interfaces.py
src/z3c/taskqueue/job.py
src/z3c/taskqueue/processor.py
src/z3c/taskqueue/processor.txt
src/z3c/taskqueue/service.py
src/z3c/taskqueue/startlater.txt
src/z3c/taskqueue/startup.py
src/z3c/taskqueue/task.py
src/z3c/taskqueue/testing.py
src/z3c/taskqueue/tests.py