Metadata-Version: 1.1
Name: z3c.taskqueue
Version: 0.2.1
Summary: Task queue service
Home-page: http://pypi.python.org/pypi/z3c.taskqueue
Author: Godefroid Chapelle and the Zope community
Author-email: zope-dev@zope.org
License: ZPL 2.1
Platform: UNKNOWN
Classifier: Programming Language :: Python
